{"animeTitle": "eikou naki tensaitachi kara monogatari", "animeType": "tv", "animeNumEpisode": "2", "releaseDate": "2017-03-25 00:00:00", "endDate": "2017-05-28 00:00:00", "animeNumMembers": "", "animeScore": "", "animeUsers": "", "animeRank": "", "animePopularity": "12425", "animeDescription": "animedocumentari seri athlet present nhk first episod adapt materi tomoyoshi itou shingo morita week young jump biograph manga eikou naki tensaitachi genius without glori \u2014specif stori hironoshin furuhashi swimmer also known fli fish fujiyama episod also includ interview olymp swimmer kousuk kitajima japanes swimmer furuhashi chang japanes competit swim world well sort train requir olymp swimmer sourc ann edit", "animeRelated": "", "animeCharacters": "", "animeVoices": "", "animeStaff": ""}