{"animeTitle": "young herlock wo oe cosmo warrior zero gaiden", "animeType": "special", "animeNumEpisode": "2", "releaseDate": "2002-06-21 00:00:00", "endDate": "", "animeNumMembers": "2154", "animeScore": "634", "animeUsers": "799", "animeRank": "7005", "animePopularity": "9229", "animeDescription": "sequel cosmo warrior zero", "animeRelated": "cosmo warrior zero", "animeCharacters": "captain herlock emeralda zero warrius maetel ooyama tochirou yattaran", "animeVoices": "", "animeStaff": "matsumoto leiji origin creator artaux cyrill adr director sirabella john execut produc"}