{"animeTitle": "tokubetsu jugyou 2", "animeType": "ova", "animeNumEpisode": "2", "releaseDate": "2003-06-13 00:00:00", "endDate": "2003-10-10 00:00:00", "animeNumMembers": "", "animeScore": "567", "animeUsers": "660", "animeRank": "", "animePopularity": "9047", "animeDescription": "colleg sacr maiden bubbl sexi young ladi perfect suit tomoya lust cross path new student professor colleg let chanc pass wast time drug guy take place danger sex fiend surround beauti buxom women alreadi got lot assign plan innoc cheerlead yumi fieri swim girl seira even asuka ravish actress one one collect pet eager sex slave fill everi burn desir girl wo nt take lie speak take tomoya twist way deepest part heart mind luscious energet bodi", "animeRelated": "tokubetsu jugyou 2 tokubetsu jugyou tokubetsu jugyou 3 slg anim", "animeCharacters": "", "animeVoices": "", "animeStaff": ""}