{"animeTitle": "fatezero onegai einzbern soudanshitsu", "animeType": "special", "animeNumEpisode": "6", "releaseDate": "2012-03-07 00:00:00", "endDate": "2012-09-19 00:00:00", "animeNumMembers": "", "animeScore": "666", "animeUsers": "14632", "animeRank": "", "animePopularity": "3098", "animeDescription": "written kinoko nasu special includ bd box set ii join irisviel help discipl zero understand detail histori relat holi grail war", "animeRelated": "fatezero fatezero 2nd season", "animeCharacters": "von einzbern irisviel fujimura taiga lancer berserk caster assassin", "animeVoices": "ohara sayaka kanemoto hisako midorikawa hikaru okiayu ryoutarou tsuruoka satoshi kawamura takuo", "animeStaff": "nasu kinoko screenplay typemoon origin creator takeuchi takashi charact design"}