{"animeTitle": "kuiba ii dazhan yuan yang jie", "animeType": "movi", "animeNumEpisode": "1", "releaseDate": "2013-05-31 00:00:00", "endDate": "", "animeNumMembers": "486", "animeScore": "646", "animeUsers": "127", "animeRank": "6350", "animePopularity": "13035", "animeDescription": "everi 333 year abomin born known kuiba destin nemesi bring disast world kuiba year 1664 sixthgener kuiba appear narrowli escap preemptiv strike forc heaven young kuiba adopt man xiaoman beast nation gave name manji like around manji unawar true ident encourag adopt father manji overcam numer trial final board warship bound maelstrom island hope prove greatest spirit warrior save world threat known kuiba meanwhil maelstrom island kuiba loyal lieuten wait readi battl oppos master return though unawar true natur manji must soon face inevit conflict father god heaven kuiba twelv fiercest lieuten sourc imdb", "animeRelated": "kuiba zhi shiwanhuoji kuiba iii zhanshen jue qi kuiba yao xia zhuan", "animeCharacters": "", "animeVoices": "", "animeStaff": ""}