{"animeTitle": "boku wa sugu ni nigetanda higashi nihon daishinsai kara mananda koto", "animeType": "ova", "animeNumEpisode": "1", "releaseDate": "2012-01-01 00:00:00", "endDate": "", "animeNumMembers": "153", "animeScore": "", "animeUsers": "", "animeRank": "15042", "animePopularity": "16882", "animeDescription": "educ video 2011 touhoku earthquak tsunami kid meant show younger kid happen everyon learn children earli memori fuzzi event even though live", "animeRelated": "", "animeCharacters": "", "animeVoices": "", "animeStaff": ""}