{"animeTitle": "sore ike anpanman tobas kibou handkerchief", "animeType": "movi", "animeNumEpisode": "1", "releaseDate": "2013-07-06 00:00:00", "endDate": "", "animeNumMembers": "262", "animeScore": "", "animeUsers": "", "animeRank": "13509", "animePopularity": "15044", "animeDescription": "25th anpanman movi screen simultan minna de teasobi anpanman itazura obak", "animeRelated": "sore ike anpanman sore ike anpanman minna de teasobi anpanman itazura obak", "animeCharacters": "anpanman baikinman chees currypanman horrorman dokinchan shokupanman melonpanna ojisan jam pao", "animeVoices": "toda keiko nakao ryusei yamadera kouichi yanagisawa michiyo kimotsuki kaneta tsuru hiromi shimamoto sumi kanai mika masuoka hiroshi motokariya yuika", "animeStaff": ""}