{"animeTitle": "alp monogatari watashi annett", "animeType": "tv", "animeNumEpisode": "48", "releaseDate": "1983-01-09 00:00:00", "endDate": "1983-12-25 00:00:00", "animeNumMembers": "", "animeScore": "673", "animeUsers": "1335", "animeRank": "", "animePopularity": "8006", "animeDescription": "12yearold annett born poor famili switzerland togeth famili live small villag alp sweet girl dear love littl 5yearold brother dani whose birth mother die also best friend lucien wonder friendship come crisi one day dani get injur terribl accid", "animeRelated": "alp monogatari watashi annett special", "animeCharacters": "burnier annett morel lucien burnier daniel burnier francin burnier pierr", "animeVoices": "han keiko yamada eiko miyuki sana masuyama eiko kobayashi osamu", "animeStaff": "kusuba kouzou director han keiko theme song perform davena cristina theme song perform aki youko theme song lyric"}