{"animeTitle": "ohoshisama rail", "animeType": "movi", "animeNumEpisode": "1", "releaseDate": "1993-07-10 00:00:00", "endDate": "", "animeNumMembers": "", "animeScore": "704", "animeUsers": "882", "animeRank": "", "animePopularity": "8294", "animeDescription": "autobiograph tale kobayashi chitos young japanes girl grow japaneseoccupi north korea world war ii progress chitos begin realiz famili abl escap effect conflict simpl disappoint abl get type backpack want school father recruit soldier war begin impact life real manner end war mean end hardship korean fed year japanes rule persecut join forc chineseback communist govern systemat make life live horror japanes left north korea fear repris sinc japanes veteran chitos father risk everyth get famili north usoccupi area south 38th parallel sourc anidb", "animeRelated": "", "animeCharacters": "", "animeVoices": "", "animeStaff": ""}