{"animeTitle": "furueru kuchibiru episod 0", "animeType": "ova", "animeNumEpisode": "1", "releaseDate": "2014-06-27 00:00:00", "endDate": "", "animeNumMembers": "7975", "animeScore": "666", "animeUsers": "3745", "animeRank": "", "animePopularity": "5827", "animeDescription": "base adult manga inu kon teacherturnedlov still communic problem make progress littl littl find answer look alreadi found sourc hmoe", "animeRelated": "furueru kuchibiru", "animeCharacters": "katakura kon", "animeVoices": "iino yuu", "animeStaff": ""}