{"animeTitle": "sai er hao season 10 bing feng yaosai", "animeType": "tv", "animeNumEpisode": "30", "releaseDate": "2019-05-30 00:00:00", "endDate": "2019-01-01 00:00:00", "animeNumMembers": "18", "animeScore": "", "animeUsers": "", "animeRank": "13027", "animePopularity": "18758", "animeDescription": "synopsi inform ad titl help improv databas ad synopsi", "animeRelated": "sai er hao season 9 pili jiuchong tian sai er hao season 11 liekong canghai", "animeCharacters": "", "animeVoices": "", "animeStaff": "", "url": "https://myanimelist.net/anime/44153/Sai_Er_Hao_Season_10__Bing_Feng_Yaosai"}