{"animeTitle": "nezha zhi mo tong jiang shi", "animeType": "movi", "animeNumEpisode": "1", "releaseDate": "2019-07-26 00:00:00", "endDate": "", "animeNumMembers": "10350", "animeScore": "763", "animeUsers": "4415", "animeRank": "1222", "animePopularity": "5255", "animeDescription": "heaven object known chao pearl two element extract spirit pearl demon orb attempt suppress power lord heaven send spirit pearl earth reincarn ne zha third son li jing demon orb schedul destroy lightn strike howev conspiraci dragon king steal spirit pearl son ne zha instead reincarn demon orb way remov curs effect demon orb ne zha rais belief becom great demon hunter spirit pearl destin fight chaotic mischiev natur ne zha must decid whether accept evil fate repel prove worthi futur parent foretold written mal rewrit", "animeRelated": "nezha nao hai jiang ziya shenhai", "animeCharacters": "ao bing ne zha shen gongbao", "animeVoices": "", "animeStaff": "", "url": "https://myanimelist.net/anime/40111/Nezha_Zhi_Mo_Tong_Jiang_Shi"}