{"animeTitle": "virgin night", "animeType": "ova", "animeNumEpisode": "1", "releaseDate": "2001-06-25 00:00:00", "endDate": "", "animeNumMembers": "3973", "animeScore": "641", "animeUsers": "1616", "animeRank": "", "animePopularity": "7659", "animeDescription": "tonight yuzuru azumi critic import date\u2014if nt becom intim end relationship may troubl conscious press matter overwhelm nervous insecur question intent written mal rewrit", "animeRelated": "virgin night", "animeCharacters": "azumi", "animeVoices": "", "animeStaff": "yoshida tomohiro sound director tanaka yutaka charact design origin creator sekiya yoshihiro director photographi hashimoto hideki anim director layout", "url": "https://myanimelist.net/anime/823/Virgin_Night"}