{"animeTitle": "zhu zhu xia da nao huang gong", "animeType": "tv", "animeNumEpisode": "4", "releaseDate": "2005-01-01 00:00:00", "endDate": "", "animeNumMembers": "157", "animeScore": "", "animeUsers": "", "animeRank": "14645", "animePopularity": "16881", "animeDescription": "seri titular charact intellig mischiev pig name gg bond \u732a\u732a\u4fa0 mean pig hero born superpow orphan care custodi dr mihu teacher enjoy invent differ gadget consid season 0 due short length origin advertis fortv movi sourc wikipedia", "animeRelated": "zhu zhu xia mo huan zhu luo ji", "animeCharacters": "", "animeVoices": "", "animeStaff": ""}