{"animeTitle": "3ping lover \u2606ippu nisai sekai e youkoso\u266a anim", "animeType": "ova", "animeNumEpisode": "1", "releaseDate": "2015-05-22 00:00:00", "endDate": "", "animeNumMembers": "12075", "animeScore": "689", "animeUsers": "5146", "animeRank": "", "animePopularity": "4934", "animeDescription": "base adult visual novel hadashi shoujo", "animeRelated": "3ping lover \u2606ippu nisai sekai e youkoso\u266a", "animeCharacters": "ringitt frey erzan alic eduaru roro lumin kuchiki tomohiro hafuringu rachel hafuringu catur", "animeVoices": "mizuguchi matsuri ogura yui haduki rie fujimoto noriko enokizu mao aoba ringo", "animeStaff": "tatsumi director storyboard charact design chief anim director ori origin creator hadashi shoujo origin creator hinasaki origin charact design", "url": "https://myanimelist.net/anime/29809/3Ping_Lovers\u2606Ippu_Nisai_no_Sekai_e_Youkoso\u266a_The_Animation"}