{"animeTitle": "madou king granzort boukenhen", "animeType": "ova", "animeNumEpisode": "3", "releaseDate": "1992-03-27 00:00:00", "endDate": "1992-06-26 00:00:00", "animeNumMembers": "412", "animeScore": "619", "animeUsers": "128", "animeRank": "7756", "animePopularity": "13493", "animeDescription": "synopsi inform ad titl help improv databas ad synopsi", "animeRelated": "madou king granzort saigo magic taisen", "animeCharacters": "rabi granzort haruka daiichi vmay yamamoto gus sutsomi okyou gus grandfath sutsomi maria", "animeVoices": "adachi shinobu ootaki shinya matsuoka youko suzuki reiko matsuda tatsuya katsuki masako ishimori takkou yokoyama chisa", "animeStaff": "kondou nobuhiro director yatat hajim origin creator ookawara kunio mechan design hiroi ouji origin creator"}