{"animeTitle": "ginga reppuu baxingar", "animeType": "tv", "animeNumEpisode": "39", "releaseDate": "1982-07-06 00:00:00", "endDate": "1983-03-29 00:00:00", "animeNumMembers": "989", "animeScore": "629", "animeUsers": "149", "animeRank": "7245", "animePopularity": "11147", "animeDescription": "600 year ginga senpuu braiger jupit destroy mani planet come bring colon combat increas lawless activ diego condor gather billi shot samanosuk dodi layla minesato shuteken radcliff aka j9ii pilot cosmo bike combin robot baxingar sourc ann", "animeRelated": "ginga senpuu braiger ginga shippuu sasuraig", "animeCharacters": "kondou diego doudi samanosuk mineri layla radcliff stecken mahoroba shirou lee fangfang lee jacki johnni jeanjacqu", "animeVoices": "tokumaru kan mori katsuji ichiryuusai harumi sogab kazuyuki shiozawa kaneto amemiya kazumi tonguu kyouko yanami jouji", "animeStaff": "nitta yoshikata director matsuura johei episod director yamagata yukio theme song perform komatsubara kazuo charact design", "url": "https://myanimelist.net/anime/4242/Ginga_Reppuu_Baxingar"}