{"animeTitle": "asa made jugyou chu", "animeType": "ova", "animeNumEpisode": "1", "releaseDate": "2012-06-23 00:00:00", "endDate": "", "animeNumMembers": "", "animeScore": "609", "animeUsers": "24557", "animeRank": "", "animePopularity": "2568", "animeDescription": "stori revolv around yuuki kagami boy enrol academi dream honor student \u2014 mistaken put girl dormitori boy prohibit face possibl leav school yuuki dress girl dormitori top thing end room femal teacher ayana kakinozaka watch", "animeRelated": "asa made jugyou chu", "animeCharacters": "kakinozaka ayana takaban risa kagami yuuki", "animeVoices": "asakura azumi mimori suzuko shimoda asami", "animeStaff": "kanazawa hiromichi director script takahashi hideo sound director mimori suzuko theme song perform asakura azumi theme song perform"}