{"animeTitle": "captain tsubasa ayaushi zen nihon jr", "animeType": "movi", "animeNumEpisode": "1", "releaseDate": "1985-12-21 00:00:00", "endDate": "", "animeNumMembers": "", "animeScore": "674", "animeUsers": "2132", "animeRank": "", "animePopularity": "7330", "animeDescription": "second movi return match europ soccer team japan begin hyuga deni join team due 3 defeat nankatsu practic hard kyra perfect tiger shot misaki ca nt come wakabayashi nt allow play normal play german team lack schneider european captain improv skill tsubasa japanes team grave problem despit new rule schneider final want beat rival wakabayashi new illus shot thus injur wakashimazu murisaki second third goal keeper brutal face shot wakabayashi final allow play cours match hyuga manag perfect tiger shot join team legendari player unit hyuga new power manag defeat oppon 43 last minut sourc ann", "animeRelated": "captain tsubasa", "animeCharacters": "oozora tsubasa wakabayashi genzou hyuuga kojirou misaki tarou schneider karlheinz nakazawa sana", "animeVoices": "suzuoki hirotaka", "animeStaff": "takahashi yoichi origin creator udagawa kazuhiko key anim okayasu hajim edit okaseko nobuhiro anim director"}