{"animeTitle": "amanchu yakusoku natsu atarashii omoid koto", "animeType": "ova", "animeNumEpisode": "1", "releaseDate": "2017-03-29 00:00:00", "endDate": "", "animeNumMembers": "14649", "animeScore": "738", "animeUsers": "6990", "animeRank": "2027", "animePopularity": "4553", "animeDescription": "unair episod bundl seventh bluray volum amanchu anim seri", "animeRelated": "amanchu amanchu advanc", "animeCharacters": "kohinata hikari ooki futaba himeno chizuru mizunashi akan katori mato ninomiya ai ninomiya makoto aria kohinata kino", "animeVoices": "suzuki eri kayano ai saitou chiwa hazuki erino itou shizuka oonishi saori umehara yuuichirou kubo yurika inou kikuko", "animeStaff": ""}