{"animeTitle": "andersen monogatari tv", "animeType": "tv", "animeNumEpisode": "52", "releaseDate": "1971-01-03 00:00:00", "endDate": "1971-12-26 00:00:00", "animeNumMembers": "836", "animeScore": "62", "animeUsers": "180", "animeRank": "7669", "animePopularity": "11581", "animeDescription": "adapt numer stori written han christian andersen", "animeRelated": "andersen monogatari", "animeCharacters": "", "animeVoices": "", "animeStaff": "", "url": "https://myanimelist.net/anime/7779/Andersen_Monogatari_TV"}