{"animeTitle": "baka mukashibanashi movi jijii war", "animeType": "movi", "animeNumEpisode": "1", "releaseDate": "2013-05-18 00:00:00", "endDate": "", "animeNumMembers": "", "animeScore": "", "animeUsers": "", "animeRank": "", "animePopularity": "14993", "animeDescription": "anim adapt old japanes folk tale modern twist keiko sootom", "animeRelated": "", "animeCharacters": "narrat", "animeVoices": "nukumizu youichi", "animeStaff": "sootom keiko director origin creator hosokawa tooru director screenplay origin creator"}