{"animeTitle": "kagaku ninyatai gatchanyan", "animeType": "ona", "animeNumEpisode": "20", "releaseDate": "2018-10-27 00:00:00", "endDate": "2019-03-21 00:00:00", "animeNumMembers": "", "animeScore": "", "animeUsers": "", "animeRank": "", "animePopularity": "13678", "animeDescription": "cat parodi kagaku ninjatai gatchaman tatsunoko product announc project nyan nyan nyan day aka cat day februari 22 earlier year charact design iwata naomi director pingu citi episod final began stream ntv various platform odd origin charact design use", "animeRelated": "kagaku ninjatai gatchaman", "animeCharacters": "", "animeVoices": "", "animeStaff": ""}