{"animeTitle": "kaleido star legend phoenix layla hamilton monogatari", "animeType": "ova", "animeNumEpisode": "1", "releaseDate": "2005-12-11 00:00:00", "endDate": "", "animeNumMembers": "", "animeScore": "787", "animeUsers": "6381", "animeRank": "", "animePopularity": "4735", "animeDescription": "layla go perform phoenix broadway play import role set journey bicycl alon without leav messag order find miss insid", "animeRelated": "kaleido star aratanaru tsubasa extra stage", "animeCharacters": "naegino sora hamilton layla fool oswald leon passel rosetta wong may killian yuri heart anna robbin ken dupont sarah", "animeVoices": "hirohashi ryou ohara sayaka koyasu takehito nakahara mai chiba susumu shimono hiro hisakawa aya", "animeStaff": "satou junichi director origin creator hiraik yoshimasa director yoshida reiko script ohara sayaka theme song perform"}