{"animeTitle": "pokemon master trainer great gather special anim", "animeType": "ona", "animeNumEpisode": "1", "releaseDate": "2019-06-27 00:00:00", "endDate": "", "animeNumMembers": "", "animeScore": "631", "animeUsers": "707", "animeRank": "", "animePopularity": "9961", "animeDescription": "origin special anim trailer made promot releas game pok\u00e9mon master sourc bulbapedia", "animeRelated": "", "animeCharacters": "takeshi mei pikachu kasumi shirona ookido green cheren erika corni", "animeVoices": "toriumi kousuk toyosaki aki sakura ayan sonozaki mie oosaka ryouta abe atsushi kayano ai minami wakana", "animeStaff": "asada yuuji director mima masafumi sound director iwan masaaki charact design nakano katsuhiro sound effect"}