{"animeTitle": "warau kangofu anim", "animeType": "ova", "animeNumEpisode": "2", "releaseDate": "2007-10-26 00:00:00", "endDate": "2008-01-25 00:00:00", "animeNumMembers": "", "animeScore": "672", "animeUsers": "2161", "animeRank": "", "animePopularity": "6678", "animeDescription": "warau kangofu nurs constant teas boy general refus neighbor men boy room constant overhear go on eventu decid go nurs second episod flashback show boy girlfriend got courag confess", "animeRelated": "warau kangofu", "animeCharacters": "hazuki miwako akan aki yumiko harada yuuji misaki", "animeVoices": "sakurai harumi hitomi", "animeStaff": "araki hideki director yonekura kengo origin creator kurata kenichi art director"}