{"animeTitle": "chibi reveng", "animeType": "ona", "animeNumEpisode": "24", "releaseDate": "2021-04-12 00:00:00", "endDate": "2021-09-20 00:00:00", "animeNumMembers": "", "animeScore": "731", "animeUsers": "2586", "animeRank": "", "animePopularity": "6399", "animeDescription": "mini anim tokyo reveng releas anim offici youtub channel", "animeRelated": "tokyo reveng", "animeCharacters": "sano manjirou ryuuguuji ken hanagaki takemichi sendou atsushi yamagishi kazushi yamamoto takuya suzuki makoto baji keisuk tachibana hinata hayashi ryouhei", "animeVoices": "terashima takuma waki azumi", "animeStaff": ""}