{"animeTitle": "prism magic prism generat", "animeType": "ova", "animeNumEpisode": "1", "releaseDate": "2010-08-27 00:00:00", "endDate": "", "animeNumMembers": "2740", "animeScore": "505", "animeUsers": "1126", "animeRank": "11384", "animePopularity": "8619", "animeDescription": "exclus ova produc pajama soft 10th anniversaryproject prism magic prism generat includ profession packag game small town sea raika enjoy school life ibuki old friend yuri maid howev father actual magic girl also group magic girl come school look treasur stone call mana prism though nt want wear girl costum forc magic girl well come back peac life save school battl magic girl start sourc anidb", "animeRelated": "prism ark", "animeCharacters": "onodera toujin wachi yuri onodera raika petit hime ibuki mikanagi bob michal harold huka mikobata sakura", "animeVoices": "imai asami nabatam hitomi sakakibara yui kuroda takaya fujimura ayumi koyama kimiko", "animeStaff": "oobari masami director episod director storyboard key anim sakakibara yui theme song perform sound music saitou maki color design"}