{"animeTitle": "fei gou moco chongwu dian de xiao mimi", "animeType": "ona", "animeNumEpisode": "97", "releaseDate": "2015-01-01 00:00:00", "endDate": "", "animeNumMembers": "19", "animeScore": "", "animeUsers": "", "animeRank": "15583", "animePopularity": "18715", "animeDescription": "synopsi inform ad titl help improv databas ad synopsi", "animeRelated": "fei gou moco", "animeCharacters": "", "animeVoices": "", "animeStaff": "", "url": "https://myanimelist.net/anime/47799/Fei_Gou_Moco__Chongwu_Dian_De_Xiao_Mimi"}