{"animeTitle": "kikumana", "animeType": "ona", "animeNumEpisode": "1", "releaseDate": "2001-07-14 00:00:00", "endDate": "", "animeNumMembers": "", "animeScore": "574", "animeUsers": "3990", "animeRank": "", "animePopularity": "5845", "animeDescription": "work kikumana anim girl call kikumana act like stage perform role defeat ill circumst though tri find primal aim get audienc feel strang atmospher spread work imag pictori atmospher documentari touch time unrealist phenomena take place sourc anidb", "animeRelated": "", "animeCharacters": "", "animeVoices": "", "animeStaff": ""}