{"animeTitle": "hitozuma cosplay kissa 2 hitozuma lovelov cosplay ova", "animeType": "ova", "animeNumEpisode": "2", "releaseDate": "2007-08-24 00:00:00", "endDate": "2007-11-22 00:00:00", "animeNumMembers": "2978", "animeScore": "64", "animeUsers": "903", "animeRank": "", "animePopularity": "8392", "animeDescription": "coffe shop sakurai small shop arcad own beauti widow sakurako number custom decreas due new amus park ocean land built near one day owner ocean land bring plan rebuild small shop arcad big shop mall sakurako oppos plan defend coffe shop full good memori husband condit stop plan collect custom coffe shop ocean land summer renew costum play coffe shop sakurai open sourc saishuucom", "animeRelated": "hitozuma cosplay kissa 2 hitozuma cosplay kissa", "animeCharacters": "itou shino saionji clair kyosuk sakurai sakurako aris mayu saionji risa koudzuki natsuki", "animeVoices": "inou miyu fujisaki kaori narumi erika oda mari sakurai harumi", "animeStaff": "ateli kaguya origin creator araki hideki anim director charact design mandm origin charact design", "url": "https://myanimelist.net/anime/3917/Hitozuma_Cosplay_Kissa_2__Hitozuma_LoveLove_-_Cosplay_OVA"}