{"animeTitle": "xi yangyang yu hui tailang kaixin fangshenshi", "animeType": "tv", "animeNumEpisode": "60", "releaseDate": "2013-07-26 00:00:00", "endDate": "", "animeNumMembers": "50", "animeScore": "", "animeUsers": "", "animeRank": "14241", "animePopularity": "18273", "animeDescription": "synopsi inform ad titl help improv databas ad synopsi", "animeRelated": "xi yangyang yu hui tailang kaixin riji xi yangyang yu hui tailang lan yangyang dang dachu", "animeCharacters": "", "animeVoices": "", "animeStaff": ""}