{"animeTitle": "eiga de utaou mother goos", "animeType": "music", "animeNumEpisode": "4", "releaseDate": "", "endDate": "", "animeNumMembers": "140", "animeScore": "", "animeUsers": "", "animeRank": "15529", "animePopularity": "17152", "animeDescription": "singalong anim meant teach japanes children english 4 dvd volum featur assort amount mother goos nurseri rhyme", "animeRelated": "", "animeCharacters": "", "animeVoices": "", "animeStaff": "", "url": "https://myanimelist.net/anime/35050/Eiga_de_Utaou_Mother_Goose"}