{"animeTitle": "issho ni h shiyo", "animeType": "ova", "animeNumEpisode": "6", "releaseDate": "2009-12-20 00:00:00", "endDate": "2011-12-09 00:00:00", "animeNumMembers": "", "animeScore": "677", "animeUsers": "3151", "animeRank": "", "animePopularity": "5458", "animeDescription": "childhood friend place spend night ask could stay place obvious agre come littl drunk upon see girlfriend fap hentai tissu decid make man sourc anidb", "animeRelated": "akina onsen de h shiyo", "animeCharacters": "miyazawa akina hamada yui natsukawa hina fukunaga aoi tsuji suzuran futaba yuuki takai haruka", "animeVoices": "tanaka ryouko enokizu mao ogura yui mizusawa kei minegishi yukari kobayashi maki kajita yuuki", "animeStaff": "watas toshihiro director episod director script storyboard screenplay miura saburou director"}