{"animeTitle": "seishun anim zenshuu", "animeType": "tv", "animeNumEpisode": "32", "releaseDate": "1986-04-25 00:00:00", "endDate": "1986-12-26 00:00:00", "animeNumMembers": "1629", "animeScore": "64", "animeUsers": "168", "animeRank": "6701", "animePopularity": "9976", "animeDescription": "brilliant collect beauti anim episod base select masterpiec japanes modern literatur aim seri appeal viewer larg give idea varieti individu japanes literatur develop last hundr year author rang higuchi ichiyou takekurab mori ougai danc girl natsum souseki botchan kawabata yasunari izu dancer nobel laureat 1968 mishima yukio sound wave sourc offici websit", "animeRelated": "bocchan seishun anim zenshuu special", "animeCharacters": "oryou narrat", "animeVoices": "imai kazuko kiuchi midori", "animeStaff": "kurokawa fumio director storyboard suda yumiko episod director miyazaki akira script nakanishi ryuuzou script"}