{"animeTitle": "examurai sengoku", "animeType": "tv", "animeNumEpisode": "24", "releaseDate": "2009-01-11 00:00:00", "endDate": "2009-06-25 00:00:00", "animeNumMembers": "", "animeScore": "629", "animeUsers": "529", "animeRank": "", "animePopularity": "7657", "animeDescription": "examurai sengoku anim product depict member exil group futurist samurai transport back time japan \u2019 sengoku war state period anim charact rendit exil member design manga creator hiroshi takahashi crow worst sourc anidb", "animeRelated": "examurai examurai sengoku recap", "animeCharacters": "atsushi matsu akira takahiro makidai usa hiro nori", "animeVoices": "tanaka hiroki kazama yuuto matsuda kenichirou masuda yuuki endou daisuk suzuki chihiro inada tetsu hiranuma norihisa", "animeStaff": "motoyama satoshi sound director takahashi hiroshi origin charact design miura kouji seri composit"}