{"animeTitle": "fight ippatsu juudenchan", "animeType": "tv", "animeNumEpisode": "12", "releaseDate": "2009-06-25 00:00:00", "endDate": "2009-09-09 00:00:00", "animeNumMembers": "30921", "animeScore": "665", "animeUsers": "12706", "animeRank": "5350", "animePopularity": "3234", "animeDescription": "meet plug unusu girl parallel world plug juudenchan capabl recharg peopl luck spread good cheer wherev goe", "animeRelated": "fight ippatsu juudenchan fight ippatsu juudenchan special fight ippatsu juudenchan ova", "animeCharacters": "cryostat plug blanket arrest oumi sento elmo rona galvani reika tomonaga iono oumi hakon tran puls chiiko narrat", "animeVoices": "fukuhara kaori takagaki ayahi takahashi hiroki hirano aya kawasumi ayako yahagi sayuri miyazaki ui tomizawa michi kaneda tomoko mitsuishi kotono", "animeStaff": "kimura shinichiro director episod director storyboard hiraik yoshimasa episod director storyboard okamoto hideki episod director storyboard yamada yasunori script seri composit"}