{"animeTitle": "uchi tama uchi tama shirimasen ka", "animeType": "tv", "animeNumEpisode": "11", "releaseDate": "2020-01-10 00:00:00", "endDate": "2020-03-20 00:00:00", "animeNumMembers": "", "animeScore": "694", "animeUsers": "4985", "animeRank": "", "animePopularity": "4077", "animeDescription": "citi somewher japan \u2019 flyer often seen third street pictur cat kink tail bear word \u201c seen tama \u201d young boy gaze flyer fluffi ear head\u2026 watch dog cat third street take human form get mischief sourc offici site", "animeRelated": "tama friend uchi tama shirimasen ka", "animeCharacters": "okamoto tama nora kawara beh noda gon yamada pochi kuramochi bull mikawa kuro hanasaki momo kiso tora oketani koma", "animeVoices": "saitou souma kaji yuki uchida yuuma hatano wataru ono kensho maeno tomoaki umehara yuuichirou hanazawa kana shirai yuusuk kurosawa tomoyo", "animeStaff": "matsuda kiyoshi director kaneko shingo storyboard hanazawa kana theme song perform kaji yuki theme song perform"}