{"animeTitle": "tottoi", "animeType": "movi", "animeNumEpisode": "1", "releaseDate": "1992-06-01 00:00:00", "endDate": "", "animeNumMembers": "", "animeScore": "618", "animeUsers": "233", "animeRank": "", "animePopularity": "11837", "animeDescription": "sensat tottoi felt discov small creatur mysteri cave beauti pride wild anim captur heart innoc peopl lost passion natur sardinia abund beauti beach mysteri cave known habitat peculiar kind seal verg extinct move island tottoi fascin natur visit differ beach cave everyday find seal cub mother isol cave surpris humor movement innoc cub digniti mother tottoi soon becom attach seal secret reveal heartless adult name preserv plan develop captur aquarium digniti pride wild seal danger matter pain tottoi separ small friend must fight welfar wild mammal let go free sea sourc offici websit", "animeRelated": "", "animeCharacters": "antonio", "animeVoices": "namikawa daisuk", "animeStaff": "nakanishi ryuuzou script mikimoto haruhiko charact design fukuda kazuya background art kaneko shuuichi inbetween anim"}