{"animeTitle": "clover", "animeType": "music", "animeNumEpisode": "1", "releaseDate": "1999-08-21 00:00:00", "endDate": "", "animeNumMembers": "", "animeScore": "678", "animeUsers": "6187", "animeRank": "", "animePopularity": "4901", "animeDescription": "suu four leaf clover power unriv yet known whole life loneli one day man name kazuhiko appear accompani suu first last journey place find happi", "animeRelated": "clover", "animeCharacters": "suu kazuhiko fay ryu lan gingetsu ko", "animeVoices": "sakamoto maaya taniyama kishou", "animeStaff": "clamp origin creator yuuki nobuteru anim director charact design hashimoto ichiko music watanab shigeru plan"}