{"animeTitle": "bomberman bdaman bakugaiden victori", "animeType": "tv", "animeNumEpisode": "50", "releaseDate": "1999-02-07 00:00:00", "endDate": "2000-01-30 00:00:00", "animeNumMembers": "1647", "animeScore": "639", "animeUsers": "628", "animeRank": "6738", "animePopularity": "9943", "animeDescription": "base hudson soft game", "animeRelated": "bomberman bdaman bakugaiden", "animeCharacters": "bomber white kurobon midoribon akabon aobon kiirobon", "animeVoices": "seki toshihiko miyazaki issei sakuma rei kozakura etsuko madono mitsuaki", "animeStaff": "tsuruoka youta sound director minakami seishi script watanab cheru theme song arrang theme song composit shiramin mitsuko theme song lyric"}