{"animeTitle": "maiotom special", "animeType": "special", "animeNumEpisode": "9", "releaseDate": "2006-01-27 00:00:00", "endDate": "2006-09-26 00:00:00", "animeNumMembers": "", "animeScore": "697", "animeUsers": "2618", "animeRank": "", "animePopularity": "6606", "animeDescription": "special follow maiotom dvd", "animeRelated": "maiotom", "animeCharacters": "kruger natsuki yumemiya arika w\u00e1ng nina tokiha mai blan de windbloom mashiro viola shizuru sayer lena armitag haruka nao zhang juliet miyu", "animeVoices": "chiba saeko kikuchi mika koshimizu ami nakahara mai yukana yuzuki ryouka", "animeStaff": "takuno seiki episod director hisayuki hirokazu charact design"}