{"animeTitle": "kodomo jikan ni gakki", "animeType": "ova", "animeNumEpisode": "3", "releaseDate": "2009-02-20 00:00:00", "endDate": "2009-07-24 00:00:00", "animeNumMembers": "29713", "animeScore": "707", "animeUsers": "16015", "animeRank": "3492", "animePopularity": "3305", "animeDescription": "second season kodomo jikan", "animeRelated": "kodomo jikan kodomo jikan tv", "animeCharacters": "kokono rin kagami kuro usa mimi aoki daisuk shirai sae kokono reiji houin kyouko oyajima kenta", "animeVoices": "kitamura eri shindou kei kadowaki mai majima junji soumi youko sugita tomokazu tanaka ryouko ishigami yuuichi", "animeStaff": "suganuma eiji director episod director storyboard iwanami yoshikazu sound director okada mari script seri composit kitamura eri theme song perform"}