{"animeTitle": "rikioh 2 horobi ko", "animeType": "ova", "animeNumEpisode": "1", "releaseDate": "1990-08-24 00:00:00", "endDate": "", "animeNumMembers": "1852", "animeScore": "522", "animeUsers": "860", "animeRank": "11087", "animePopularity": "9643", "animeDescription": "child destruct sequel rikioh ova wall hell child destruct tell us riki past flash back childhood learn terribl fate mother taken away twin brother nachi game hideandseek nachi plaintiv cri readi yet haunt year riki sixpoint star emblazon hand nachi swastika signific go unexplain riki find town misaki dot illeg nuclear power plant run religi fanat militari organ call god judgment taken prison made fight gladiatori match sprawl arena find brother whose special power given name savior reunion resent sibl turn sour rather quick part 2 much gorier part 1 riki smash fist numer soldier oppon far less restraint sourc imdb", "animeRelated": "rikioh rikioh toukatsu jigoku", "animeCharacters": "saiga rikioh nachi", "animeVoices": "shimada bin ikeda shuuichi", "animeStaff": "kamimura osamu storyboard sakamoto eizou theme song perform nakajima yuuki theme song arrang sugino akio charact design", "url": "https://myanimelist.net/anime/3511/Riki-Oh_2__Horobi_no_Ko"}