{"animeTitle": "pittarazu gekijou manner cm", "animeType": "special", "animeNumEpisode": "9", "releaseDate": "2013-09-07 00:00:00", "endDate": "2014-08-23 00:00:00", "animeNumMembers": "72", "animeScore": "", "animeUsers": "", "animeRank": "12782", "animePopularity": "18104", "animeDescription": "pittarazuthem manner movi shown tjoy own theater around japan first four shown august 7 2013 novemb 1 2013 includ special pittarazu dvds begin august 23 2014 five manner movi shown theater nine manner movi later post dle offici youtub channel", "animeRelated": "pittarazu", "animeCharacters": "", "animeVoices": "", "animeStaff": "", "url": "https://myanimelist.net/anime/42542/Pittarazu_Gekijou_Manner_CM"}