{"animeTitle": "maetel legend", "animeType": "ova", "animeNumEpisode": "2", "releaseDate": "2000-12-13 00:00:00", "endDate": "2001-03-07 00:00:00", "animeNumMembers": "3784", "animeScore": "64", "animeUsers": "1373", "animeRank": "6686", "animePopularity": "7781", "animeDescription": "artifici sun light frozen planet la metall die threaten extinguish littl life left queen la andromeda prometheum decid way peopl surviv submit hardgear transform process turn everyon bodi machin queen daughter emeralda maetel refus submit process fight stay human sourc ann", "animeRelated": "uchuu koukyoushi maetel ginga tetsudou 999 gaiden ginga tetsudou 999 shin taketori monogatari 1000nen joou 1000nen joou queen millennia herlock saga nibelung yubiwa queen emeralda zero seiki movi 3 maetel", "animeCharacters": "maetel emeralda promethium ii la andromeda hardgear", "animeVoices": "yukino satsuki enomoto atsuko han keiko matsuyama takashi", "animeStaff": "hayas hiroyuki sound director matsumoto leiji origin creator amano masamichi music matsuda akihiko sound effect", "url": "https://myanimelist.net/anime/1495/Maetel_Legend"}