{"animeTitle": "genki ekodachan", "animeType": "tv", "animeNumEpisode": "22", "releaseDate": "2011-04-13 00:00:00", "endDate": "2011-09-14 00:00:00", "animeNumMembers": "887", "animeScore": "575", "animeUsers": "114", "animeRank": "9575", "animePopularity": "11431", "animeDescription": "base fourpanel manga rinshi ekodachan singl woman tokyo drift relationship work various hostess club like sourc zigguratbuild edit", "animeRelated": "rinshi ekodachan", "animeCharacters": "ekodachan", "animeVoices": "", "animeStaff": "takinami yukari origin creator", "url": "https://myanimelist.net/anime/10540/Genki_Ekoda-chan"}