{"animeTitle": "tansu warashi", "animeType": "movi", "animeNumEpisode": "1", "releaseDate": "2011-03-05 00:00:00", "endDate": "", "animeNumMembers": "", "animeScore": "678", "animeUsers": "3238", "animeRank": "", "animePopularity": "6808", "animeDescription": "noel hiiragi think life stress enough live alon work call center mother send sixdraw wardrob blue hope return furnitur attempt stuff corner tini apart call mother complain sudden burden mom vagu tell noel turn noel return night drink find fat child apart eat food shock confus eventu discov mother wardrob contain six strang children claim serv current mistress hiiragi famili refus buy blunt explan noel struggl adapt new lifestyl wonder whether children servic bless curs written mal rewrit", "animeRelated": "kizuna ichigeki ojiisan lamp bannou yasai ninninman", "animeCharacters": "hiiragi noel natsuki masa jirokichi daigorou hanpei tae yuki", "animeVoices": "noto mamiko ono fuyuka takato yasuhiro matsumoto megumi kozakura etsuko ueda kana konno hiromi", "animeStaff": "kise kazuchika director charact design key anim koizumi kisuk sound director ishikawa mitsuhisa plan tanimura daishiro screenplay"}