{"animeTitle": "3pun de wakaru kore made love live sunshin", "animeType": "ona", "animeNumEpisode": "1", "releaseDate": "2018-11-18 00:00:00", "endDate": "", "animeNumMembers": "2094", "animeScore": "615", "animeUsers": "591", "animeRank": "7922", "animePopularity": "9335", "animeDescription": "3minut special recap promot movi love live sunshin school idol movi rainbow", "animeRelated": "love live sunshin love live sunshin 2nd season", "animeCharacters": "", "animeVoices": "", "animeStaff": "", "url": "https://myanimelist.net/anime/41189/3-pun_de_Wakaru_Kore_made_no_Love_Live_Sunshine"}