{"animeTitle": "fatestay night unlimit blade work 2nd season", "animeType": "tv", "animeNumEpisode": "13", "releaseDate": "2015-04-05 00:00:00", "endDate": "2015-06-28 00:00:00", "animeNumMembers": "714551", "animeScore": "833", "animeUsers": "463799", "animeRank": "207", "animePopularity": "176", "animeDescription": "midst fifth holi grail war caster set plan motion begin captur shirou servant saber witch grow ever power rin archer determin threat must dealt balanc power war begin shift master servant find walk separ way meanwhil despit lose servant stumbl injuri shirou ignor rin warn abandon battl royal forc way fight caster determin show resolv fight shirou potenti becom protector peopl put test amidst bloodsh chao motiv master servant slowli reveal sacrific everyth order aris victor claim holi grail written mal rewrit", "animeRelated": "fatestay night unlimit blade work fatestay night unlimit blade work 2nd season sunni day", "animeCharacters": "saber toosaka rin gilgamesh archer emiya shirou von einzbern illyasviel kotomin kirei lancer velvet waver caster", "animeVoices": "kawasumi ayako ueda kana seki tomokazu suwab junichi sugiyama noriaki kadowaki mai nakata jouji canna nobutoshi namikawa daisuk tanaka atsuko", "animeStaff": "iwakami atsuhiro produc kondou hikaru produc miura takahiro director storyboard iwanami yoshikazu sound director", "url": "https://myanimelist.net/anime/28701/Fate_stay_night__Unlimited_Blade_Works_2nd_Season"}