{"animeTitle": "mardock scrambl third exhaust", "animeType": "movi", "animeNumEpisode": "1", "releaseDate": "2012-09-29 00:00:00", "endDate": "", "animeNumMembers": "32619", "animeScore": "743", "animeUsers": "16198", "animeRank": "1884", "animePopularity": "3160", "animeDescription": "final plan finish shell court made easter balot oeufcoqu order execut plan must set foot shell domain blueegg casino center mardock citi find chip memori lie ca nt find chip case dismiss court use gone \u2013 result death balot find chip time still dodg boil mad search oeufcoqu sourc witch theatrego", "animeRelated": "mardock scrambl mardock scrambl second combust", "animeCharacters": "balot rune penteano \u0153ufcoqu boil dimsdal septino shell dr easter harvest ashley wing bell fever marlow john", "animeVoices": "hayashibara megumi yashima norito isob tsutomu nakai kazuya touchi hiroki fujita toshiko ono daisuk", "animeStaff": "nakanishi go produc kudou susumu director episod director storyboard mima masafumi sound director hayashibara megumi theme song perform", "url": "https://myanimelist.net/anime/12053/Mardock_Scramble__The_Third_Exhaust"}