{"animeTitle": "taiman blue ladieshen mayumi", "animeType": "ova", "animeNumEpisode": "2", "releaseDate": "1990-04-05 00:00:00", "endDate": "1990-05-25 00:00:00", "animeNumMembers": "", "animeScore": "", "animeUsers": "", "animeRank": "", "animePopularity": "13600", "animeDescription": "fifteenyearold mayumi move rough end osaka parent split remarri meet noriko help settl new life noriko job petrol station got know big bear biker gang eventu get gang girl racer sourc anim encyclopedia", "animeRelated": "taiman blue shimizu naotohen", "animeCharacters": "", "animeVoices": "", "animeStaff": ""}