{"animeTitle": "kimagur robot", "animeType": "tv", "animeNumEpisode": "10", "releaseDate": "2004-12-22 00:00:00", "endDate": "", "animeNumMembers": "2195", "animeScore": "60", "animeUsers": "999", "animeRank": "8631", "animePopularity": "9181", "animeDescription": "brilliant slight crazi extrem eccentr scientist toil away day lab creat robot carri differ task robot grant three wish robot help write diari robot intent misbehav order keep master becom bored\u2026 robot built specif purpos \u2019 realli much anyth els luckili mankind howev robot much use appear first glance\u2026 time anyway sourc ann", "animeRelated": "", "animeCharacters": "doctor assist", "animeVoices": "itakura toshiyuki matsumoto rio", "animeStaff": "itou nobutak director ashino yoshiharu director uratani chie director hoshi shinichi origin creator"}