{"animeTitle": "jigoku shoujo yoi togi", "animeType": "tv", "animeNumEpisode": "6", "releaseDate": "2017-07-15 00:00:00", "endDate": "2017-08-19 00:00:00", "animeNumMembers": "50249", "animeScore": "657", "animeUsers": "15481", "animeRank": "5772", "animePopularity": "2490", "animeDescription": "grudg someon access hell correspond websit stroke midnight type grudg name hell girl ai enma appear grant wish howev price rid burden steep one return condemn soul tormentor hell soul also face etern damnat long vigil hell girl ai met mani will pay cost jigoku shoujo yoi togi ai enigmat companion continu carri work ferri soul suffer soul depth hell howev late mysteri girl follow strang child unabl even rememb ident question ai duti hell girl girl connect ai written mal rewrit", "animeRelated": "jigoku shoujo mitsugana", "animeCharacters": "enma ai ichimoku ren hone onna kikuri wanyuudou yamawaro michiru shibata tsugumi hanagasa mamoru", "animeVoices": "noto mamiko matsukaz masaya honda takako sakai kanako sugou takayuki shiina hekiru watada misaki", "animeStaff": "oomori takahiro director omata shinichi storyboard nishimoto yukio storyboard noto mamiko theme song perform"}