{"animeTitle": "koikishi purely\u2606kiss anim", "animeType": "ova", "animeNumEpisode": "2", "releaseDate": "2013-07-26 00:00:00", "endDate": "2014-02-28 00:00:00", "animeNumMembers": "", "animeScore": "718", "animeUsers": "5247", "animeRank": "", "animePopularity": "4513", "animeDescription": "past children kanam elcia caught build fire broken elcia got stuck rubbl kanam nt plan give even though seem hopeless kanam run strength modernday knight save incid decid promis becom knight protect uphold justic righteous year later fulfil promis work sidebysid protect uphold justic love start grow heart", "animeRelated": "koikishi purely\u2606kiss elicia chikai koikishi purely\u2606kiss yuu negai", "animeCharacters": "haven elicia fujimori yuu fujimori kanam kazama akari shidou mana kuninaka kaori", "animeVoices": "tanaka ryouko fukada ai ogura yui miruno jun narumi erika", "animeStaff": "nishikawa takashi director charact design yuuki hagur origin charact design horikawa kazuto director photographi katahira shinji art director"}