{"animeTitle": "saishuu chikan densha next", "animeType": "ova", "animeNumEpisode": "2", "releaseDate": "2012-07-27 00:00:00", "endDate": "2012-10-26 00:00:00", "animeNumMembers": "5097", "animeScore": "665", "animeUsers": "1702", "animeRank": "", "animePopularity": "6941", "animeDescription": "year 2010 reprehens secret brotherhood known last molest train driven underground three year reign sexual predat extinguish milit ultrafeminist organ known raven guard howev yet lost last molest train continu search savior could restor patriarchi glori long last man found sourc vndb", "animeRelated": "saishuu chikan densha 3 shin saishuu chikan densha", "animeCharacters": "takatori jin kurotaki rin odagiri naomi", "animeVoices": "sawamiya naho katou masami", "animeStaff": "hayakawa naomi director episod director storyboard charact design ateli kaguya origin creator shonai mai color design akatsuki shion anim director charact design"}