{"animeTitle": "vs knight lamun 40 fresh", "animeType": "ova", "animeNumEpisode": "6", "releaseDate": "1997-05-21 00:00:00", "endDate": "1997-11-21 00:00:00", "animeNumMembers": "2323", "animeScore": "566", "animeUsers": "877", "animeRank": "9894", "animePopularity": "9035", "animeDescription": "save galaxi impend doom cacao parfait sent mission time space retriev fourth warrior lamun unfortun cacao parfait discov lamun helm maraud giga geno invas fleet world world lamun determin bring entir galaxi tyrann heel help plicki orphan cacao parfait stop lamun take world", "animeRelated": "vs knight lamun 40 fire", "animeCharacters": "parfait cacao", "animeVoices": "miyamura yuko hikami kyouko", "animeStaff": "fujimoto yoshitaka director kaida yuriko theme song perform hasegawa katsumi screenplay kishimoto seiji mechan design", "url": "https://myanimelist.net/anime/1411/VS_Knight_Lamune___40_Fresh"}