{"animeTitle": "doukyuusei 2 ova", "animeType": "ova", "animeNumEpisode": "12", "releaseDate": "1996-03-22 00:00:00", "endDate": "1996-12-18 00:00:00", "animeNumMembers": "", "animeScore": "561", "animeUsers": "350", "animeRank": "", "animePopularity": "9980", "animeDescription": "base game elf", "animeRelated": "doukyuusei ova climax doukyuusei 2 ova special sotsugyousei", "animeCharacters": "narusawa yui mooroka wataru tanaka misa", "animeVoices": "tachibana hikari", "animeStaff": "kageyama shigenori director elf corpor origin creator rinshin charact design ooshiro tsutomu key anim"}