{"animeTitle": "dennou boukenki webdiv", "animeType": "tv", "animeNumEpisode": "52", "releaseDate": "2001-04-06 00:00:00", "endDate": "2002-03-23 00:00:00", "animeNumMembers": "2142", "animeScore": "691", "animeUsers": "768", "animeRank": "4155", "animePopularity": "9244", "animeDescription": "set year 2100 world tie togeth comput network children world becom web diver adapt conscious data love play togeth cyber park call magic gate howev mysteri comput virus appear begin destroy magic gate insid cyberspac program call web knight creat protect children comput virus turn web knight children web knight escap brainwash gladion gladion seek help kaito yuki web diver fourth grade sourc ann", "animeRelated": "", "animeCharacters": "asaba naoki kurachi shou gladion yuuki kaito yuuki kento jacquard jeanjacqu arisugawa aoi", "animeVoices": "takeuchi junko kaida yuki sugita tomokazu kobayashi yumiko kikuchi shiho", "animeStaff": "okajima kunitoshi director episod director storyboard tanaka hideyuki sound director kageyama hironobu theme song perform hayashi yuzo music", "url": "https://myanimelist.net/anime/3561/Dennou_Boukenki_Webdiver"}