{"animeTitle": "one piec episod sorajima", "animeType": "special", "animeNumEpisode": "1", "releaseDate": "2018-08-25 00:00:00", "endDate": "", "animeNumMembers": "22475", "animeScore": "715", "animeUsers": "9247", "animeRank": "3106", "animePopularity": "3807", "animeDescription": "special first episod seri cover skypeia arc featur charact appear origin skypeia arc anim sourc ann", "animeRelated": "one piec", "animeCharacters": "monkey luffi roronoa zoro sanji nico robin toni toni chopper usopp nami enel montblanc norland wiper", "animeVoices": "tanaka mayumi nakai kazuya hirata hiroaki yamaguchi yuriko ootani iku yamaguchi kappei okamura akemi morikawa toshiyuki ootsuka houchuu kiuchi reiko", "animeStaff": "uda kounosuk director endou tetsuya director oda eiichiro origin creator satou masayuki charact design"}